[
  {
    "id": "reviewer-2026",
    "date": "2026-04-17",
    "title": "Serving as a reviewer for ISMAR and UIST 2026",
    "icon": "fa-pen-nib",
    "tags": [
      "UIST",
      "ISMAR",
      "Reviewer"
    ],
    "body": "I will be serving as a reviewer for the ISMAR 2026 and UIST 2026 conference. Honored to contribute to the HCI community."
  },
  {
    "id": "chi26-presentation",
    "date": "2026-04-15",
    "title": "I presented my paper ConCon at Barcelona!",
    "icon": "fa-bullhorn",
    "tags": [
      "CHI",
      "Publication",
      "Presentation"
    ],
    "body": "I presented a paper titled \"ConCon: A Wrist-Worn Clutch-Coupled Force-Feedback Device for VR Controller\" in Barcelona. I was also able to see many other interesting research projects and demos. The open-hardware GitHub repository for ConCon is planned to be updated within May."
  },
  {
    "id": "phd, admission",
    "date": "2026-03-03",
    "title": "I started my career as a PhD Student in HCI Lab!",
    "icon": "fa-newspaper",
    "tags": [
      "PhD",
      "KAIST",
      "HCI Lab"
    ],
    "body": "I have started my PhD in the same lab. I would like to continue working on a variety of research projects in the future!"
  },
  {
    "id": "master-thesis-prize",
    "date": "2026-01-30",
    "title": "I got an outstanding MS Thesis in School of Computing, KAIST for Year 2025!",
    "thumbnail": "images/news/soc-logo.png",
    "tags": [
      "Thesis",
      "Award"
    ],
    "body": "I got a certificate of achievement for an outstanding MS Thesis! It is related to the paper that was accepted to the CHI'26! You can see the device named ConCon and its open-hardware with demo Unity scene in upcomming April!"
  },
  {
    "id": "chi2026-paper",
    "date": "2026-01-16",
    "title": "ConCon accepted to CHI 2026",
    "thumbnail": "images/news/chi26-logo.png",
    "tags": [
      "CHI",
      "paper"
    ],
    "body": "Our paper, <span class=\\\"font-semibold\\\">\\\"ConCon: A Wrist-Worn Clutch-Coupled Force-Feedback Device for VR Controller\\\"</span>, was accepted to CHI 2026! Looking forward to presenting our work in Barcelona!"
  },
  {
    "id": "uist2025-presentation",
    "date": "2025-09-27",
    "title": "I presented my paper StringTouch at Busan",
    "thumbnail": "images/news/uist-presentation.png",
    "tags": [
      "UIST",
      "paper presentation"
    ],
    "body": "I presented the paper \"StringTouch: A Non-occlusive 3DoF Haptic Interface Using String Structures for Modulating Finger Sensations\" in UIST 2025, Busan. You can find the paper in ACM DL or this hompage!"
  },
  {
    "id": "ict2025-prize",
    "date": "2025-09-15",
    "title": "Our Team (Geppetto) won the Minister's Award for ICT Challenge 2025",
    "thumbnail": "images/news/geppetto-image.png",
    "tags": [
      "Award"
    ],
    "body": "Our Team (Me, Kyunghwan, Taejun from KAIST HCI Lab) presented ConCon, which is a wrist-grounded 3DoF force feedback device compatible with existing VR controllers, enabling realistic haptic interactions without extra tracking, and won the Minister's Award for ICT Challenge 2025 in Republic of Korea!"
  },
  {
    "id": "uist2025-stringtouch",
    "date": "2025-08-14",
    "title": "StringTouch accepted to UIST 2025",
    "thumbnail": "images/news/uist2025-logo.png",
    "tags": [
      "UIST",
      "Publication"
    ],
    "body": "Our paper, <span class=\"font-semibold\">\"StringTouch: A Non-occlusive 3DoF Haptic Interface Using String Structures for Modulating Finger Sensations\"</span>, was accepted to UIST 2025. Looking forward to presenting our work in Busan!"
  },
  {
    "id": "ismar2025-reviewer",
    "date": "2025-06-05",
    "title": "Serving as a reviewer for ISMAR 2025",
    "thumbnail": "images/news/ismar-reviewer.png",
    "tags": [
      "Service",
      "ISMAR"
    ],
    "body": "I will be serving as a reviewer for the ISMAR 2025 conference. Honored to contribute to the HCI community."
  },
  {
    "id": "chi2025-otmouse",
    "date": "2025-03-20",
    "title": "OtMouse accepted to CHI 2025",
    "thumbnail": "images/news/chi2025-logo.png",
    "tags": [
      "CHI",
      "Publication"
    ],
    "body": "Our paper, <span class=\"font-semibold\">\"Over the Mouse: Navigating across the GUI with Finger‑Lifting Operation Mouse\"</span>, was accepted to CHI 2025!"
  }
]